{
    "InputFile": "DocumentDefinitions/Templates/document-template.md",
    "BuildPath": "build/Templates/NFE/",
    "Title": "Niet-Functionele Eisen",
    "Subtitle": "{Productnaam, versie}",
    "DocumentType": "Template",
    "DocumentFolder": "NFE",
    "FrontPage": "Neutral",
    "IncludeTableOfContents": true,
    "OutputFormats": {
        "docx": {
            "OutputFile": "Neutraal-Template-Niet-Functionele-Eisen.docx",
            "OutputPaths": [
                "docs/wip"
            ],
            "ReferenceFile": "DocumentDefinitions/reference-neutral.docx"
        }
    },
    "VariablesFiles": [
        "DocumentDefinitions/Shared/variables.json"
    ]
}